prefect_managedfiletransfer/AssetDownloadResult.py
prefect_managedfiletransfer/FileMatcher.py
prefect_managedfiletransfer/FileToFolderMapping.py
prefect_managedfiletransfer/PathUtil.py
prefect_managedfiletransfer/RCloneCommandBuilder.py
prefect_managedfiletransfer/RCloneConfig.py
prefect_managedfiletransfer/RCloneConfigFileBlock.py
prefect_managedfiletransfer/RCloneConfigSavedInPrefect.py
prefect_managedfiletransfer/RemoteAsset.py
prefect_managedfiletransfer/RemoteConnectionType.py
prefect_managedfiletransfer/ServerWithBasicAuthBlock.py
prefect_managedfiletransfer/ServerWithPublicKeyAuthBlock.py
prefect_managedfiletransfer/SortFilesBy.py
prefect_managedfiletransfer/TransferType.py
prefect_managedfiletransfer/__init__.py
prefect_managedfiletransfer/block_utils.py
prefect_managedfiletransfer/constants.py
prefect_managedfiletransfer/delete_asset.py
prefect_managedfiletransfer/delete_file_task.py
prefect_managedfiletransfer/delete_files_flow.py
prefect_managedfiletransfer/deploy.py
prefect_managedfiletransfer/download_asset.py
prefect_managedfiletransfer/download_file_task.py
prefect_managedfiletransfer/ensure_space.py
prefect_managedfiletransfer/invoke_rclone.py
prefect_managedfiletransfer/list_remote_assets.py
prefect_managedfiletransfer/list_remote_files_task.py
prefect_managedfiletransfer/main.py
prefect_managedfiletransfer/password_utils.py
prefect_managedfiletransfer/sftp_utils.py
prefect_managedfiletransfer/tasks.py
prefect_managedfiletransfer/time_util.py
prefect_managedfiletransfer/transfer_files_flow.py
prefect_managedfiletransfer/unpack_files_flow.py
prefect_managedfiletransfer/upload_asset.py
prefect_managedfiletransfer/upload_file_flow.py
prefect_managedfiletransfer/upload_file_task.py
prefect_managedfiletransfer/rclone/rclone
prefect_managedfiletransfer/rclone/rclone.exe
prefect_managedfiletransfer/rclone/osx/rclone
prefect_managedfiletransfer-0.4.1.dist-info/licenses/LICENSE
prefect_managedfiletransfer-0.4.1.dist-info/METADATA
prefect_managedfiletransfer-0.4.1.dist-info/WHEEL
prefect_managedfiletransfer-0.4.1.dist-info/entry_points.txt
prefect_managedfiletransfer-0.4.1.dist-info/top_level.txt
prefect_managedfiletransfer-0.4.1.dist-info/RECORD
