Metadata-Version: 2.4
Name: prefect-managedfiletransfer
Version: 0.4.1
Summary: Upload, download, and delete files easily between Local/SFTP/Cloud storage using rclone
Author-email: Alastair Crabtree <a.crabtree@imperial.ac.uk>
License-Expression: Apache-2.0
Project-URL: Homepage, https://github.com/ImperialCollegeLondon/prefect-managedfiletransfer
Keywords: prefect,file,copy,move,transfer,delete,SFTP,rclone
Classifier: Intended Audience :: Developers
Classifier: Intended Audience :: System Administrators
Classifier: Natural Language :: English
Classifier: Programming Language :: Python :: 3 :: Only
Classifier: Programming Language :: Python :: 3.10
Classifier: Programming Language :: Python :: 3.11
Classifier: Programming Language :: Python :: 3.12
Classifier: Topic :: Software Development :: Libraries
Requires-Python: >=3.10
License-File: LICENSE
Requires-Dist: prefect>=3.1.7
Requires-Dist: pydantic>=2.11.0a2
Requires-Dist: paramiko>=4.0.0
Dynamic: license-file
